__init__.py
sys_conf.py
system_config_tools-0.0.2.dist-info/LICENSE
system_config_tools-0.0.2.dist-info/METADATA
system_config_tools-0.0.2.dist-info/WHEEL
system_config_tools-0.0.2.dist-info/top_level.txt
system_config_tools-0.0.2.dist-info/RECORD
